{
 "playerId": "2574406",
 "name": "Tyler Shough",
 "team": "NO",
 "pos": "QB",
 "opponent": "TB",
 "home": false,
 "gameId": "2025_14_NO_TB",
 "gamesPlayed2025": 5,
 "props": [
  {
   "market": "pass_yds",
   "projection": 214.5,
   "quantiles": {
    "p10": 100.6,
    "p25": 150.5,
    "p50": 217.7,
    "p75": 256.1,
    "p90": 308.5
   },
   "probCurve": [
    {
     "line": 80.0,
     "over": 0.98
    },
    {
     "line": 85.0,
     "over": 0.9662
    },
    {
     "line": 90.0,
     "over": 0.9506
    },
    {
     "line": 95.0,
     "over": 0.9269
    },
    {
     "line": 100.0,
     "over": 0.9029
    },
    {
     "line": 105.0,
     "over": 0.8868
    },
    {
     "line": 110.0,
     "over": 0.8718
    },
    {
     "line": 115.0,
     "over": 0.8567
    },
    {
     "line": 120.0,
     "over": 0.8417
    },
    {
     "line": 125.0,
     "over": 0.8267
    },
    {
     "line": 130.0,
     "over": 0.8117
    },
    {
     "line": 135.0,
     "over": 0.7966
    },
    {
     "line": 140.0,
     "over": 0.7816
    },
    {
     "line": 145.0,
     "over": 0.7666
    },
    {
     "line": 150.0,
     "over": 0.7516
    },
    {
     "line": 155.0,
     "over": 0.7333
    },
    {
     "line": 160.0,
     "over": 0.7147
    },
    {
     "line": 165.0,
     "over": 0.6961
    },
    {
     "line": 170.0,
     "over": 0.6775
    },
    {
     "line": 175.0,
     "over": 0.6589
    },
    {
     "line": 180.0,
     "over": 0.6403
    },
    {
     "line": 185.0,
     "over": 0.6217
    },
    {
     "line": 190.0,
     "over": 0.6031
    },
    {
     "line": 195.0,
     "over": 0.5845
    },
    {
     "line": 200.0,
     "over": 0.5659
    },
    {
     "line": 205.0,
     "over": 0.5473
    },
    {
     "line": 210.0,
     "over": 0.5287
    },
    {
     "line": 215.0,
     "over": 0.5101
    },
    {
     "line": 220.0,
     "over": 0.4851
    },
    {
     "line": 225.0,
     "over": 0.4526
    },
    {
     "line": 230.0,
     "over": 0.42
    },
    {
     "line": 235.0,
     "over": 0.3875
    },
    {
     "line": 240.0,
     "over": 0.355
    },
    {
     "line": 245.0,
     "over": 0.3225
    },
    {
     "line": 250.0,
     "over": 0.29
    },
    {
     "line": 255.0,
     "over": 0.2575
    },
    {
     "line": 260.0,
     "over": 0.239
    },
    {
     "line": 265.0,
     "over": 0.2247
    },
    {
     "line": 270.0,
     "over": 0.2103
    },
    {
     "line": 275.0,
     "over": 0.196
    },
    {
     "line": 280.0,
     "over": 0.1817
    },
    {
     "line": 285.0,
     "over": 0.1674
    },
    {
     "line": 290.0,
     "over": 0.1531
    },
    {
     "line": 295.0,
     "over": 0.1388
    },
    {
     "line": 300.0,
     "over": 0.1245
    },
    {
     "line": 305.0,
     "over": 0.1101
    },
    {
     "line": 310.0,
     "over": 0.097
    },
    {
     "line": 315.0,
     "over": 0.0867
    },
    {
     "line": 320.0,
     "over": 0.0765
    },
    {
     "line": 325.0,
     "over": 0.0662
    },
    {
     "line": 330.0,
     "over": 0.0559
    },
    {
     "line": 335.0,
     "over": 0.0471
    },
    {
     "line": 340.0,
     "over": 0.0404
    },
    {
     "line": 345.0,
     "over": 0.0337
    },
    {
     "line": 350.0,
     "over": 0.0269
    },
    {
     "line": 355.0,
     "over": 0.0202
    }
   ],
   "refLine": 238.5,
   "overProbAtRef": 0.3648,
   "lean": "under",
   "strength": 23,
   "confidence": "medium",
   "confidenceReason": "Decent 5-game sample, but with some week-to-week swing.",
   "verdict": "The model projects 215 passing yards \u2014 it gives Tyler a 36% chance to clear a 238.5-yard line.",
   "factors": [
    {
     "group": "game_environment",
     "direction": "down",
     "impact": -38.9,
     "label": "Vegas pegs this at 41.5 total points, about 17 for the Saints",
     "detail": "The expected scoring script nudges the projection down by about 39 yards."
    },
    {
     "group": "usage_role",
     "direction": "down",
     "impact": -21.6,
     "label": "His offense throws about 35 passes a game",
     "detail": "How often the team drops back nudges the projection down by about 22 yards."
    },
    {
     "group": "opp_defense",
     "direction": "up",
     "impact": 17.2,
     "label": "Tampa Bay gives up 266 passing yards a game \u2014 4th most in the NFL",
     "detail": "A matchup this generous nudges the projection up by about 17 yards."
    },
    {
     "group": "recent_form",
     "direction": "up",
     "impact": 5.6,
     "label": "Averaging 254.7 passing yards over his last 3 games",
     "detail": "That's up from 213.6 across his last 8; stacked against a typical week at his position, his form nudges the projection up by about 6 yards."
    },
    {
     "group": "weather",
     "direction": "up",
     "impact": 5.1,
     "label": "Fair conditions \u2014 about 73 degrees, 6 mph wind",
     "detail": "Nothing scary in the forecast; weather nudges the projection up by about 5 yards."
    }
   ],
   "actual": 144.0,
   "result": "under"
  },
  {
   "market": "pass_tds",
   "projection": 1.1,
   "quantiles": {
    "p10": 0.0,
    "p25": 0.5,
    "p50": 1.1,
    "p75": 2.0,
    "p90": 3.1
   },
   "probCurve": [
    {
     "line": 0.5,
     "over": 0.7475
    },
    {
     "line": 1.5,
     "over": 0.3627
    },
    {
     "line": 2.5,
     "over": 0.1475
    },
    {
     "line": 3.5,
     "over": 0.052
    },
    {
     "line": 4.5,
     "over": 0.0115
    }
   ],
   "refLine": 0.5,
   "overProbAtRef": 0.7475,
   "lean": "over",
   "strength": 35,
   "confidence": "low",
   "confidenceReason": "His week-to-week range has been wide, so take this one loosely.",
   "verdict": "The model expects 1.1 touchdown passes \u2014 it gives Tyler a 75% chance to go over 0.5.",
   "factors": [
    {
     "group": "game_environment",
     "direction": "down",
     "impact": -0.21,
     "label": "Vegas pegs this at 41.5 total points, about 17 for the Saints",
     "detail": "The expected scoring script nudges the projection down by about 0.21 touchdown passes."
    },
    {
     "group": "usage_role",
     "direction": "down",
     "impact": -0.08,
     "label": "His offense throws about 35 passes a game",
     "detail": "How often the team drops back nudges the projection down by about 0.08 touchdown passes."
    },
    {
     "group": "weather",
     "direction": "up",
     "impact": 0.07,
     "label": "Fair conditions \u2014 about 73 degrees, 6 mph wind",
     "detail": "Nothing scary in the forecast; weather nudges the projection up by about 0.07 touchdown passes."
    },
    {
     "group": "home_away",
     "direction": "up",
     "impact": 0.05,
     "label": "On the road at Tampa Bay",
     "detail": "The road trip nudges the projection up by about 0.05 touchdown passes."
    },
    {
     "group": "qb_situation",
     "direction": "up",
     "impact": 0.04,
     "label": "5 starts this season under his belt",
     "detail": "How settled the QB job is nudges the projection up by about 0.04 touchdown passes."
    },
    {
     "group": "opp_defense",
     "direction": "down",
     "impact": -0.04,
     "label": "Tampa Bay gives up 2 touchdown passes a game \u2014 9th most in the NFL",
     "detail": "The season-long numbers lean generous, but recent defensive form and how they fare against his position count for more here \u2014 on balance the matchup nudges the projection down by about 0.04 touchdown passes."
    }
   ],
   "actual": 0.0,
   "result": "under"
  }
 ],
 "recentGames": [
  {
   "season": 2025,
   "week": 13,
   "opponent": "MIA",
   "home": false,
   "stats": {
    "pass_yds": 239.0,
    "pass_tds": 2.0,
    "rush_yds": 18.0,
    "rec_yds": 0.0,
    "receptions": 0.0
   }
  },
  {
   "season": 2025,
   "week": 12,
   "opponent": "ATL",
   "home": true,
   "stats": {
    "pass_yds": 243.0,
    "pass_tds": 0.0,
    "rush_yds": 22.0,
    "rec_yds": 0.0,
    "receptions": 0.0
   }
  },
  {
   "season": 2025,
   "week": 10,
   "opponent": "CAR",
   "home": false,
   "stats": {
    "pass_yds": 282.0,
    "pass_tds": 2.0,
    "rush_yds": -3.0,
    "rec_yds": 0.0,
    "receptions": 0.0
   }
  },
  {
   "season": 2025,
   "week": 9,
   "opponent": "LA",
   "home": false,
   "stats": {
    "pass_yds": 176.0,
    "pass_tds": 1.0,
    "rush_yds": 2.0,
    "rec_yds": 0.0,
    "receptions": 0.0
   }
  },
  {
   "season": 2025,
   "week": 8,
   "opponent": "TB",
   "home": true,
   "stats": {
    "pass_yds": 128.0,
    "pass_tds": 0.0,
    "rush_yds": 12.0,
    "rec_yds": 0.0,
    "receptions": 0.0
   }
  }
 ],
 "seasonAvgs": {
  "pass_yds": 213.6,
  "pass_tds": 1.0,
  "rush_yds": 10.2
 },
 "modelHistory": [
  {
   "week": 13,
   "market": "pass_tds",
   "projection": 0.8,
   "refLine": 0.5,
   "lean": "neutral",
   "actual": 2.0,
   "result": "over"
  },
  {
   "week": 13,
   "market": "pass_yds",
   "projection": 185.4,
   "refLine": 209.5,
   "lean": "under",
   "actual": 239.0,
   "result": "over"
  },
  {
   "week": 12,
   "market": "pass_tds",
   "projection": 1.0,
   "refLine": 0.5,
   "lean": "over",
   "actual": 0.0,
   "result": "under"
  },
  {
   "week": 12,
   "market": "pass_yds",
   "projection": 208.0,
   "refLine": 176.5,
   "lean": "over",
   "actual": 243.0,
   "result": "over"
  },
  {
   "week": 10,
   "market": "pass_tds",
   "projection": 0.2,
   "refLine": 0.5,
   "lean": "under",
   "actual": 2.0,
   "result": "over"
  },
  {
   "week": 10,
   "market": "pass_yds",
   "projection": 186.8,
   "refLine": 152.5,
   "lean": "over",
   "actual": 282.0,
   "result": "over"
  }
 ]
}